strace_process_tree.py
strace_process_tree-1.5.2.dist-info/licenses/LICENSE
strace_process_tree-1.5.2.dist-info/METADATA
strace_process_tree-1.5.2.dist-info/WHEEL
strace_process_tree-1.5.2.dist-info/entry_points.txt
strace_process_tree-1.5.2.dist-info/top_level.txt
strace_process_tree-1.5.2.dist-info/RECORD
